cronista/__init__.py
cronista/core.py
cronista-0.0.9.dist-info/METADATA
cronista-0.0.9.dist-info/WHEEL
cronista-0.0.9.dist-info/top_level.txt
cronista-0.0.9.dist-info/RECORD
