Metadata-Version: 2.4
Name: cronista
Version: 0.0.9
Summary: Record function calls with composable logs and Maybe results (cronista: a Python port of chronicler)
Author: Bruno Rodrigues
License: GPL-3.0-or-later
Project-URL: Homepage, https://github.com/b-rodrigues/cronista
Project-URL: Bug Tracker, https://github.com/b-rodrigues/cronista/issues
Keywords: logging,pipeline,maybe,functional programming,reproducibility
Classifier: Programming Language :: Python :: 3
Classifier: License :: OSI Approved :: GNU General Public License v3 (GPLv3)
Classifier: Operating System :: OS Independent
Requires-Python: >=3.8
Requires-Dist: talvez>=0.0.9
Provides-Extra: pandas
Requires-Dist: pandas>=2.0; extra == "pandas"
